Metadata-Version: 1.1
Name: fastdtw
Version: 0.3.0
Summary: Dynamic Time Warping (DTW) algorithm with an O(N) time and memory complexity.
Home-page: https://github.com/slaypni/fastdtw
Author: Kazuaki Tanida
Author-email: UNKNOWN
License: MIT
Keywords: dtw
Platform: UNKNOWN
Classifier: Programming Language :: Python :: 2
Classifier: Programming Language :: Python :: 3
Classifier: Intended Audience :: Science/Research
Classifier: License :: OSI Approved :: MIT License
Classifier: Topic :: Scientific/Engineering
